gptdiff/__init__.py
gptdiff/applydiff.py
gptdiff/gptdiff.py
gptdiff/gptpatch.py
gptdiff/gptsummarize.py
gptdiff/plangptdiff.py
gptdiff-0.5.2.dist-info/licenses/LICENSE.txt
gptdiff-0.5.2.dist-info/METADATA
gptdiff-0.5.2.dist-info/WHEEL
gptdiff-0.5.2.dist-info/entry_points.txt
gptdiff-0.5.2.dist-info/top_level.txt
gptdiff-0.5.2.dist-info/RECORD
